woah/__init__.py
woah/cmdline.py
woah/tests/__init__.py
woah/tests/__main__.py
woah/tests/test_cmdline.py
woah-0.2.dist-info/LICENSE
woah-0.2.dist-info/METADATA
woah-0.2.dist-info/WHEEL
woah-0.2.dist-info/entry_points.txt
woah-0.2.dist-info/top_level.txt
woah-0.2.dist-info/RECORD
